ckvn/__init__.py
ckvn/api.py
ckvn/utils.py
ckvn-0.0.1.dist-info/LICENSE
ckvn-0.0.1.dist-info/METADATA
ckvn-0.0.1.dist-info/WHEEL
ckvn-0.0.1.dist-info/top_level.txt
ckvn-0.0.1.dist-info/RECORD
