Metadata-Version: 2.2
Name: ckvn
Version: 0.0.1
Summary: Python module to interact with stock data via Django API
Home-page: https://github.com/ckvnpro/ckvn
Author: CKVN
Author-email: ckvnpro@gmail.com
Classifier: Programming Language :: Python :: 3
Classifier: License :: OSI Approved :: MIT License
Classifier: Operating System :: OS Independent
Requires-Python: >=3.6
License-File: LICENSE
Requires-Dist: requests
Dynamic: author
Dynamic: author-email
Dynamic: classifier
Dynamic: description
Dynamic: description-content-type
Dynamic: home-page
Dynamic: requires-dist
Dynamic: requires-python
Dynamic: summary
